[{"action": "open", "author": {"author.email": "marekjm@ozro.pw", "author.name": "Marek Marecki"}, "timestamp": 1545173195.152739}, {"action": "set-message", "params": {"text": "Specify nested function rules\n\nThis is somethat similar to the closure issue, but a little bit easier\nsince nested functions do not capture their environment.\n\nAlso, they are not created dynamically (as closures are) but are normal\nfunctions; just not visible inside the module scope."}, "author": {"author.email": "marekjm@ozro.pw", "author.name": "Marek Marecki"}, "timestamp": 1545173195.152749}, {"action": "push-tags", "params": {"tags": []}, "author": {"author.email": "marekjm@ozro.pw", "author.name": "Marek Marecki"}, "timestamp": 1545173195.152751}, {"action": "push-milestones", "params": {"milestones": []}, "author": {"author.email": "marekjm@ozro.pw", "author.name": "Marek Marecki"}, "timestamp": 1545173195.152753}]